[
    {
        "nama": "asa",
        "email": "alfiahsanitaqwim06@gmail.com",
        "alamat": "sfas",
        "jurusan": "jwd",
        "tahun": "2003"
    },
    {
        "nama": "asa",
        "email": "alfiahsanitaqwim06@gmail.com",
        "alamat": "sby",
        "jurusan": "cc",
        "tahun": "2018"
    },
    {
        "nama": "asa",
        "email": "alfiahsanitaqwim06@gmail.com",
        "alamat": "das",
        "jurusan": "jwd",
        "tahun": "2003"
    },
    {
        "nama": "asa",
        "email": "alfiahsanitaqwim06@gmail.com",
        "alamat": "gh",
        "jurusan": "jwd",
        "tahun": "2002"
    },
    {
        "nama": "asa",
        "email": "alfiahsanitaqwim06@gmail.com",
        "alamat": "sad",
        "jurusan": "jwd",
        "tahun": "2001"
    },
    {
        "nama": "Cotton bud",
        "email": "alfiahsanitaqwim06@gmail.com",
        "alamat": "gjh",
        "jurusan": "jwd",
        "tahun": "2023"
    }
]